{
  "id": "abd9b8f4-8316-43cd-8f57-e9ad70c7ac9f",
  "prevId": "3193055b-6eed-4bca-ac3c-0af02244f7df",
  "version": "7",
  "dialect": "postgresql",
  "tables": {
    "public.brokers": {
      "name": "brokers",
      "schema": "",
      "columns": {
        "id": {
          "name": "id",
          "type": "uuid",
          "primaryKey": true,
          "notNull": true,
          "default": "gen_random_uuid()"
        },
        "clerk_user_id": {
          "name": "clerk_user_id",
          "type": "text",
          "primaryKey": false,
          "notNull": true
        },
        "name": {
          "name": "name",
          "type": "text",
          "primaryKey": false,
          "notNull": true
        },
        "cash_balance_cents": {
          "name": "cash_balance_cents",
          "type": "bigint",
          "primaryKey": false,
          "notNull": true,
          "default": 0
        },
        "created_at": {
          "name": "created_at",
          "type": "timestamp with time zone",
          "primaryKey": false,
          "notNull": true,
          "default": "now()"
        },
        "updated_at": {
          "name": "updated_at",
          "type": "timestamp with time zone",
          "primaryKey": false,
          "notNull": true,
          "default": "now()"
        }
      },
      "indexes": {},
      "foreignKeys": {},
      "compositePrimaryKeys": {},
      "uniqueConstraints": {
        "brokers_clerk_user_id_unique": {
          "name": "brokers_clerk_user_id_unique",
          "columns": ["clerk_user_id"],
          "nullsNotDistinct": false
        }
      },
      "policies": {},
      "checkConstraints": {},
      "isRLSEnabled": false
    },
    "public.orders": {
      "name": "orders",
      "schema": "",
      "columns": {
        "id": {
          "name": "id",
          "type": "uuid",
          "primaryKey": true,
          "notNull": true,
          "default": "gen_random_uuid()"
        },
        "sequence": {
          "name": "sequence",
          "type": "bigserial",
          "primaryKey": false,
          "notNull": true
        },
        "broker_id": {
          "name": "broker_id",
          "type": "uuid",
          "primaryKey": false,
          "notNull": true
        },
        "owner_document": {
          "name": "owner_document",
          "type": "text",
          "primaryKey": false,
          "notNull": true
        },
        "symbol": {
          "name": "symbol",
          "type": "text",
          "primaryKey": false,
          "notNull": true
        },
        "side": {
          "name": "side",
          "type": "order_side",
          "typeSchema": "public",
          "primaryKey": false,
          "notNull": true
        },
        "type": {
          "name": "type",
          "type": "order_type",
          "typeSchema": "public",
          "primaryKey": false,
          "notNull": true
        },
        "limit_price_cents": {
          "name": "limit_price_cents",
          "type": "bigint",
          "primaryKey": false,
          "notNull": false
        },
        "quantity": {
          "name": "quantity",
          "type": "integer",
          "primaryKey": false,
          "notNull": true
        },
        "remaining": {
          "name": "remaining",
          "type": "integer",
          "primaryKey": false,
          "notNull": true
        },
        "status": {
          "name": "status",
          "type": "order_status",
          "typeSchema": "public",
          "primaryKey": false,
          "notNull": true,
          "default": "'open'"
        },
        "created_at": {
          "name": "created_at",
          "type": "timestamp with time zone",
          "primaryKey": false,
          "notNull": true,
          "default": "now()"
        },
        "updated_at": {
          "name": "updated_at",
          "type": "timestamp with time zone",
          "primaryKey": false,
          "notNull": true,
          "default": "now()"
        },
        "expires_at": {
          "name": "expires_at",
          "type": "timestamp with time zone",
          "primaryKey": false,
          "notNull": false
        }
      },
      "indexes": {
        "orders_book_idx": {
          "name": "orders_book_idx",
          "columns": [
            {
              "expression": "symbol",
              "isExpression": false,
              "asc": true,
              "nulls": "last"
            },
            {
              "expression": "side",
              "isExpression": false,
              "asc": true,
              "nulls": "last"
            },
            {
              "expression": "status",
              "isExpression": false,
              "asc": true,
              "nulls": "last"
            }
          ],
          "isUnique": false,
          "with": {},
          "method": "btree",
          "concurrently": false
        },
        "orders_broker_idx": {
          "name": "orders_broker_idx",
          "columns": [
            {
              "expression": "broker_id",
              "isExpression": false,
              "asc": true,
              "nulls": "last"
            }
          ],
          "isUnique": false,
          "with": {},
          "method": "btree",
          "concurrently": false
        }
      },
      "foreignKeys": {
        "orders_broker_id_brokers_id_fk": {
          "name": "orders_broker_id_brokers_id_fk",
          "tableFrom": "orders",
          "columnsFrom": ["broker_id"],
          "tableTo": "brokers",
          "columnsTo": ["id"],
          "onUpdate": "no action",
          "onDelete": "no action"
        },
        "orders_symbol_stocks_symbol_fk": {
          "name": "orders_symbol_stocks_symbol_fk",
          "tableFrom": "orders",
          "columnsFrom": ["symbol"],
          "tableTo": "stocks",
          "columnsTo": ["symbol"],
          "onUpdate": "no action",
          "onDelete": "no action"
        }
      },
      "compositePrimaryKeys": {},
      "uniqueConstraints": {},
      "policies": {},
      "checkConstraints": {},
      "isRLSEnabled": false
    },
    "public.stocks": {
      "name": "stocks",
      "schema": "",
      "columns": {
        "symbol": {
          "name": "symbol",
          "type": "text",
          "primaryKey": true,
          "notNull": true
        },
        "name": {
          "name": "name",
          "type": "text",
          "primaryKey": false,
          "notNull": true
        },
        "created_at": {
          "name": "created_at",
          "type": "timestamp with time zone",
          "primaryKey": false,
          "notNull": true,
          "default": "now()"
        }
      },
      "indexes": {},
      "foreignKeys": {},
      "compositePrimaryKeys": {},
      "uniqueConstraints": {},
      "policies": {},
      "checkConstraints": {},
      "isRLSEnabled": false
    },
    "public.trades": {
      "name": "trades",
      "schema": "",
      "columns": {
        "id": {
          "name": "id",
          "type": "uuid",
          "primaryKey": true,
          "notNull": true,
          "default": "gen_random_uuid()"
        },
        "symbol": {
          "name": "symbol",
          "type": "text",
          "primaryKey": false,
          "notNull": true
        },
        "price_cents": {
          "name": "price_cents",
          "type": "bigint",
          "primaryKey": false,
          "notNull": true
        },
        "quantity": {
          "name": "quantity",
          "type": "integer",
          "primaryKey": false,
          "notNull": true
        },
        "bid_order_id": {
          "name": "bid_order_id",
          "type": "uuid",
          "primaryKey": false,
          "notNull": true
        },
        "ask_order_id": {
          "name": "ask_order_id",
          "type": "uuid",
          "primaryKey": false,
          "notNull": true
        },
        "bid_broker_id": {
          "name": "bid_broker_id",
          "type": "uuid",
          "primaryKey": false,
          "notNull": true
        },
        "ask_broker_id": {
          "name": "ask_broker_id",
          "type": "uuid",
          "primaryKey": false,
          "notNull": true
        },
        "executed_at": {
          "name": "executed_at",
          "type": "timestamp with time zone",
          "primaryKey": false,
          "notNull": true,
          "default": "now()"
        }
      },
      "indexes": {
        "trades_symbol_idx": {
          "name": "trades_symbol_idx",
          "columns": [
            {
              "expression": "symbol",
              "isExpression": false,
              "asc": true,
              "nulls": "last"
            },
            {
              "expression": "executed_at",
              "isExpression": false,
              "asc": true,
              "nulls": "last"
            }
          ],
          "isUnique": false,
          "with": {},
          "method": "btree",
          "concurrently": false
        }
      },
      "foreignKeys": {
        "trades_symbol_stocks_symbol_fk": {
          "name": "trades_symbol_stocks_symbol_fk",
          "tableFrom": "trades",
          "columnsFrom": ["symbol"],
          "tableTo": "stocks",
          "columnsTo": ["symbol"],
          "onUpdate": "no action",
          "onDelete": "no action"
        },
        "trades_bid_order_id_orders_id_fk": {
          "name": "trades_bid_order_id_orders_id_fk",
          "tableFrom": "trades",
          "columnsFrom": ["bid_order_id"],
          "tableTo": "orders",
          "columnsTo": ["id"],
          "onUpdate": "no action",
          "onDelete": "no action"
        },
        "trades_ask_order_id_orders_id_fk": {
          "name": "trades_ask_order_id_orders_id_fk",
          "tableFrom": "trades",
          "columnsFrom": ["ask_order_id"],
          "tableTo": "orders",
          "columnsTo": ["id"],
          "onUpdate": "no action",
          "onDelete": "no action"
        },
        "trades_bid_broker_id_brokers_id_fk": {
          "name": "trades_bid_broker_id_brokers_id_fk",
          "tableFrom": "trades",
          "columnsFrom": ["bid_broker_id"],
          "tableTo": "brokers",
          "columnsTo": ["id"],
          "onUpdate": "no action",
          "onDelete": "no action"
        },
        "trades_ask_broker_id_brokers_id_fk": {
          "name": "trades_ask_broker_id_brokers_id_fk",
          "tableFrom": "trades",
          "columnsFrom": ["ask_broker_id"],
          "tableTo": "brokers",
          "columnsTo": ["id"],
          "onUpdate": "no action",
          "onDelete": "no action"
        }
      },
      "compositePrimaryKeys": {},
      "uniqueConstraints": {},
      "policies": {},
      "checkConstraints": {},
      "isRLSEnabled": false
    },
    "public.webhook_deliveries": {
      "name": "webhook_deliveries",
      "schema": "",
      "columns": {
        "id": {
          "name": "id",
          "type": "uuid",
          "primaryKey": true,
          "notNull": true,
          "default": "gen_random_uuid()"
        },
        "endpoint_id": {
          "name": "endpoint_id",
          "type": "uuid",
          "primaryKey": false,
          "notNull": true
        },
        "trade_id": {
          "name": "trade_id",
          "type": "uuid",
          "primaryKey": false,
          "notNull": true
        },
        "status": {
          "name": "status",
          "type": "webhook_delivery_status",
          "typeSchema": "public",
          "primaryKey": false,
          "notNull": true,
          "default": "'pending'"
        },
        "attempts": {
          "name": "attempts",
          "type": "integer",
          "primaryKey": false,
          "notNull": true,
          "default": 0
        },
        "last_error": {
          "name": "last_error",
          "type": "text",
          "primaryKey": false,
          "notNull": false
        },
        "created_at": {
          "name": "created_at",
          "type": "timestamp with time zone",
          "primaryKey": false,
          "notNull": true,
          "default": "now()"
        },
        "updated_at": {
          "name": "updated_at",
          "type": "timestamp with time zone",
          "primaryKey": false,
          "notNull": true,
          "default": "now()"
        }
      },
      "indexes": {},
      "foreignKeys": {
        "webhook_deliveries_endpoint_id_webhook_endpoints_id_fk": {
          "name": "webhook_deliveries_endpoint_id_webhook_endpoints_id_fk",
          "tableFrom": "webhook_deliveries",
          "columnsFrom": ["endpoint_id"],
          "tableTo": "webhook_endpoints",
          "columnsTo": ["id"],
          "onUpdate": "no action",
          "onDelete": "no action"
        },
        "webhook_deliveries_trade_id_trades_id_fk": {
          "name": "webhook_deliveries_trade_id_trades_id_fk",
          "tableFrom": "webhook_deliveries",
          "columnsFrom": ["trade_id"],
          "tableTo": "trades",
          "columnsTo": ["id"],
          "onUpdate": "no action",
          "onDelete": "no action"
        }
      },
      "compositePrimaryKeys": {},
      "uniqueConstraints": {},
      "policies": {},
      "checkConstraints": {},
      "isRLSEnabled": false
    },
    "public.webhook_endpoints": {
      "name": "webhook_endpoints",
      "schema": "",
      "columns": {
        "id": {
          "name": "id",
          "type": "uuid",
          "primaryKey": true,
          "notNull": true,
          "default": "gen_random_uuid()"
        },
        "broker_id": {
          "name": "broker_id",
          "type": "uuid",
          "primaryKey": false,
          "notNull": true
        },
        "url": {
          "name": "url",
          "type": "text",
          "primaryKey": false,
          "notNull": true
        },
        "secret": {
          "name": "secret",
          "type": "text",
          "primaryKey": false,
          "notNull": true
        },
        "active": {
          "name": "active",
          "type": "boolean",
          "primaryKey": false,
          "notNull": true,
          "default": true
        },
        "created_at": {
          "name": "created_at",
          "type": "timestamp with time zone",
          "primaryKey": false,
          "notNull": true,
          "default": "now()"
        }
      },
      "indexes": {},
      "foreignKeys": {
        "webhook_endpoints_broker_id_brokers_id_fk": {
          "name": "webhook_endpoints_broker_id_brokers_id_fk",
          "tableFrom": "webhook_endpoints",
          "columnsFrom": ["broker_id"],
          "tableTo": "brokers",
          "columnsTo": ["id"],
          "onUpdate": "no action",
          "onDelete": "no action"
        }
      },
      "compositePrimaryKeys": {},
      "uniqueConstraints": {},
      "policies": {},
      "checkConstraints": {},
      "isRLSEnabled": false
    }
  },
  "enums": {
    "public.order_side": {
      "name": "order_side",
      "schema": "public",
      "values": ["bid", "ask"]
    },
    "public.order_status": {
      "name": "order_status",
      "schema": "public",
      "values": ["open", "partially_filled", "filled", "cancelled", "expired"]
    },
    "public.order_type": {
      "name": "order_type",
      "schema": "public",
      "values": ["limit", "market"]
    },
    "public.webhook_delivery_status": {
      "name": "webhook_delivery_status",
      "schema": "public",
      "values": ["pending", "delivered", "failed"]
    }
  },
  "schemas": {},
  "views": {},
  "sequences": {},
  "roles": {},
  "policies": {},
  "_meta": {
    "columns": {},
    "schemas": {},
    "tables": {}
  }
}
